LICENSE
filewrap/__init__.py
filewrap/py.typed
python_filewrap-0.2.8.2.dist-info/LICENSE
python_filewrap-0.2.8.2.dist-info/METADATA
python_filewrap-0.2.8.2.dist-info/WHEEL
python_filewrap-0.2.8.2.dist-info/RECORD
